<?xml version="1.0" encoding="UTF-8"?><?xml-stylesheet type='text/xsl' href='_UpgradeReport_Files/UpgradeReport.xslt'?><UpgradeLog>
<Properties><Property Name="Solution" Value="SharpSerializer">
</Property><Property Name="Solution File" Value="C:\Users\dozorca\Documents\Visual Studio 2010\Projects\SharpSerializer\SharpSerializer.sln">
</Property><Property Name="Date" Value="Freitag, 21. März 2014">
</Property><Property Name="Time" Value="05:35">
</Property></Properties><Event ErrorLevel="0" Project="SharpSerializer.Library" Source="SharpSerializer.Library\SharpSerializer.Library.csproj" Description="The project file does not require conversion.">
</Event><Event ErrorLevel="3" Project="SharpSerializer.Library" Source="SharpSerializer.Library\SharpSerializer.Library.csproj" Description="No Conversion Required">
</Event><Event ErrorLevel="0" Project="HelloWorldApp" Source="HelloWorldApp\HelloWorldApp.csproj" Description="The project file does not require conversion.">
</Event><Event ErrorLevel="3" Project="HelloWorldApp" Source="HelloWorldApp\HelloWorldApp.csproj" Description="No Conversion Required">
</Event><Event ErrorLevel="0" Project="SharpSerializer.Library.Silverlight" Source="SharpSerializer.Library.Silverlight\SharpSerializer.Library.Silverlight.csproj" Description="Project converted successfully">
</Event><Event ErrorLevel="3" Project="SharpSerializer.Library.Silverlight" Source="SharpSerializer.Library.Silverlight\SharpSerializer.Library.Silverlight.csproj" Description="Converted">
</Event><Event ErrorLevel="0" Project="SharpSerializer.Library.Compact" Source="SharpSerializer.Library.Compact\SharpSerializer.Library.Compact.csproj" Description="Project converted successfully">
</Event><Event ErrorLevel="3" Project="SharpSerializer.Library.Compact" Source="SharpSerializer.Library.Compact\SharpSerializer.Library.Compact.csproj" Description="Converted">
</Event><Event ErrorLevel="0" Project="SharpSerializer.Tests" Source="SharpSerializer.Tests\SharpSerializer.Tests.csproj" Description="Project converted successfully">
</Event><Event ErrorLevel="3" Project="SharpSerializer.Tests" Source="SharpSerializer.Tests\SharpSerializer.Tests.csproj" Description="Converted">
</Event><Event ErrorLevel="0" Project="" Source="SharpSerializer.sln" Description="Solution converted successfully">
</Event><Event ErrorLevel="3" Project="" Source="SharpSerializer.sln" Description="Converted">
</Event><Event ErrorLevel="0" Project="SharpSerializer.Library.Silverlight" Source="SharpSerializer.Library.Silverlight\SharpSerializer.Library.Silverlight.csproj" Description="Scan complete: Upgrade not required for project files.">
</Event><Event ErrorLevel="0" Project="SharpSerializer.Tests" Source="SharpSerializer.Tests\SharpSerializer.Tests.csproj" Description="Scan complete: Upgrade not required for project files.">
</Event></UpgradeLog>